LICENSE
NOTICE
README.md
fleepit.py
setup.py
fleepit.egg-info/PKG-INFO
fleepit.egg-info/SOURCES.txt
fleepit.egg-info/dependency_links.txt
fleepit.egg-info/entry_points.txt
fleepit.egg-info/top_level.txt