Metadata-Version: 2.1
Name: fleepit
Version: 6
Summary: Text seleciton keyboard layout switcher based on xclip / etc for X11 & wayland
Home-page: https://git.pegasko.art/bitrate16/fleepit
Author-email: pegasko@pegasko.art
License: Apache 2.0
Keywords: keyboard layout shortcut layout-switcher
License-File: LICENSE
License-File: NOTICE
